Workbook

Sheet Construct
B3: Particulars
B4: Relationship | C4: Employer-Employee Group
B5: Description of group | C5: Corporates which have employer employee relationship (7-100 lives)
B6: Master Policy Holder | C6: Each Client
B7: Intermediary | C7: Safetynet Insurance Services (Healthysure)
B8: Product Details
B9: Product | C9: GMC
B10: Mandatory vs Voluntary | C10: Mandatory for all employees
B11: Contributory/Non Contributory | C11: Non Contributory
B12: Premium | C12: Annual Basis
B13: Min Lives | C13: 7 lives
B14: Max Lives | C14: 100 lives
B15: Maternity Option | C15: Yes (Min. 10 employees for maternity)
B16: Graded Sum Insured | C16: Not Permissible
B17: Commission % | C17: Mark-up upto 25%
B18: T&C | C18: For renewal cases - 1. Exclusive mandate is required 2. Loss ratio should be less than or equal to 75% For Fresh cases - 1. Exclusive mandate is required
B19: Administration
B20: Endorsements Calculation | C20: Pro-rata Basis
B21: Documents required for policy issuance | C21: 1. PAN 2. GST 3. Proposal Form 4. Member Data 5. Canceled Cheque 6. Expired policy copy (applicable for renewal cases) 7. Claims History 8. Declaration of all employees are covered (maintained by HS) 9. Spoc Details
B22: TAT | C22: 7-10 working days for policy issuance 2-3 working days for endorsements

Sheet Coverages
B2: Features | C2: Base Plan
B5: Family Definition | C5: Self only OR Self , Spouse, Children upto 25 years (max 4 children)
B6: Age Band | C6: 18 - 60 years entry age Can renew upto 65 years
B7: Premium | C7: Per life basis
B8: Sum Insured | C8: 1L/ 2L/ 3L/ 5L
B9: Policy Type | C9: Floater
B10: Co-Pay | C10: 0% for All
B11: Room Rent Restriction | C11: For SI 1 lac - Rs. 2,000 for Normal, Rs. 4,000 for ICU For SI 2 lac/ 3 lac - Rs. 5,000 for Normal, Rs. 10,000 for ICU For SI 5 lac - Single Private AC
B12: Daycare Treatments | C12: Covered (All Procedures)
B13: Disease Capping | C13: NIL
B14: Pre and Post Hospitalization (medicines, lab tests and consultations) | C14: 60/90 days (For in-patient Hospitalization)
B15: Initial Waiting Period | C15: NIL
... B32: Other Considerations | C32: • 50% Co-Pay for Cyber Knife treatment, Gamma Knife treatment, Robotic Surgery • 50% Co Pay for Stem Cell Transplantation • Lasik covered above +/- 6.5 • Terrorism is covered

Sheet Pricing E only
A1: Per life premium rates exclusive of GST
B3: Family Definition | C3: Self Only
B5: Commission | C5: 0 | D5: Mark-up upto 25%
B7: Age Band / Sum Insured | C7: 100000 | D7: 200000 | E7: 300000 | F7: 500000
B8: [18-25] | C8: 1182 | D8: 1633 | E8: 2100 | F8: 2969
B9: [26-35] | C9: 1580 | D9: 2178 | E9: 2794 | F9: 3944 | H9: =E9*21 -> 58674 | I9: 32727
B10: [36-45] | C10: 2184 | D10: 3004 | E10: 3846 | F10: 5424 | H10: =H9*1.25 -> 73342.5 | I10: =H9+I9 -> 91401
B11: [46-50] | C11: 2841 | D11: 3903 | E11: 4992 | F11: 7034 | I11: =I10*1.25 -> 114251.25
B12: [51-55] | C12: 3602 | D12: 4946 | E12: 6319 | F12: 8900 | I12: =I10/0.75 -> 121868
B13: [56-60] | C13: 4854 | D13: 6660 | E13: 8503 | F13: 11970

Sheet Pricing ESC
A1: Per life premium rates exclusive of GST
B3: Family Definition | C3: Self, Spouse, Children upto 25 years (max 4 children)
B5: Commission | C5: 0 | D5: Mark-up upto 25%
B7: Age Band / Sum Insured | C7: 100000 | D7: 200000 | E7: 300000 | F7: 500000
B8: [0-5] | C8: 1878 | D8: 2583 | E8: 3310 | F8: 4666
B9: [6-17] | C9: 996 | D9: 1377 | E9: 1775 | F9: 2510
B10: [18-25] | C10: =ROUND('Pricing E only'!C8*1.2,0) -> 1418 | D10: =ROUND('Pricing E only'!D8*1.2,0) -> 1960 | E10: =ROUND('Pricing E only'!E8*1.2,0) -> 2520 | F10: =ROUND('Pricing E only'!F8*1.2,0) -> 3563
B11: [26-35] | C11: =ROUND('Pricing E only'!C9*1.2,0) -> 1896 | D11: =ROUND('Pricing E only'!D9*1.2,0) -> 2614 | E11: =ROUND('Pricing E only'!E9*1.2,0) -> 3353 | F11: =ROUND('Pricing E only'!F9*1.2,0) -> 4733 | G11: =E11*21 -> 70413
B12: [36-45] | C12: =ROUND('Pricing E only'!C10*1.2,0) -> 2621 | D12: =ROUND('Pricing E only'!D10*1.2,0) -> 3605 | E12: =ROUND('Pricing E only'!E10*1.2,0) -> 4615 | F12: =ROUND('Pricing E only'!F10*1.2,0) -> 6509 | G12: =E9*3 -> 5325
B13: [46-50] | C13: =ROUND('Pricing E only'!C11*1.2,0) -> 3409 | D13: =ROUND('Pricing E only'!D11*1.2,0) -> 4684 | E13: =ROUND('Pricing E only'!E11*1.2,0) -> 5990 | F13: =ROUND('Pricing E only'!F11*1.2,0) -> 8441 | G13: 32727.34
B14: [51-55] | C14: =ROUND('Pricing E only'!C12*1.2,0) -> 4322 | D14: =ROUND('Pricing E only'!D12*1.2,0) -> 5935 | E14: =ROUND('Pricing E only'!E12*1.2,0) -> 7583 | F14: =ROUND('Pricing E only'!F12*1.2,0) -> 10680 | G14: =SUM(G11:G13) -> 108465.34
B15: [56-60] | C15: =ROUND('Pricing E only'!C13*1.2,0) -> 5825 | D15: =ROUND('Pricing E only'!D13*1.2,0) -> 7992 | E15: =ROUND('Pricing E only'!E13*1.2,0) -> 10204 | F15: =ROUND('Pricing E only'!F13*1.2,0) -> 14364 | G15: =G14/0.75 -> 144620.45

Sheet Loadings&Discounts
B1: Discounts applicable on premium rates, basis the corresponding age band
B3: Maternity Cover (Normal & C-Section and New Born expenses covered up to maternity sum insured)
B4: Loadings for maternity to be added to premium rates, basis corresponding age bands (appicable for only female self and female spouse)
B6: Commission | C6: 0
B8: Age Band / SI | C8: 35000 | D8: 50000 | E8: 75000
B9: [18-25] | C9: 3326.008 | D9: 3778.5765 | E9: 5913.1737
B10: [26-35] | C10: 3353.5712 | D10: 4090.9175 | E10: 6542.4405 | G10: =D10*8 -> 32727.34
B11: [36-45] | C11: 734.95737 | D11: 844.76745 | E11: 1358.4047
B14: Discounts applicable on base premium rates (i.e., premium rates without maternity)
B16: Location-based discount
B18: Location | C18: Discount
B19: Mumbai | C19: 0
B20: Thane | C20: 0
B21: Delhi/NCR | C21: 0
B22: Noida | C22: 0
B23: Gurgaon | C23: 0
B24: Faridabad | C24: 0
B25: Ghaziabad | C25: 0
B26: Ahmedabad | C26: 0
B27: Surat | C27: 0
B28: Varodra | C28: 0
B29: Pune | C29: 0
B30: Cochin | C30: 0
... B35: Other | C35: 0.1

Sheet Industry List - Non Gig workers
B2: Industry | C2: Master Policy - Non Gig
B3: Accountant/Auditors/CA | C3: 1
B4: Airline Crew and Airport Ground Staff | C4: 1
B5: Artist/Painter/writers | C5: 1
B6: Automobile (Non manufacturing) | C6: 1
B7: Banker | C7: 1
B8: Banks,Financial Institutions and other NBFC including insurance | C8: 1
B9: Civil Servant/Bureaucrats | C9: 1
B10: Consultants working in office premises | C10: 1
B11: Designers | C11: 1
B12: Desk Jobs | C12: 1
B13: IT,Servicing, Telecom, BPO | C13: 1
B14: Legal Professionals | C14: 1
... B19: Small SME Merchants | C19: 1
B20: Please note: This is illustrative and not an exhaustive list

Sheet Industry List - Gig Workers
B2: Industry | C2: Master Policy - Gig Workers
B3: Agro Industry/Food Processing/Dairy/FMCG | C3: 2
B4: Chefs/Commercial Kitchen Workers | C4: 2
B5: Clerk, pantry boy, peon etc | C5: 2
B6: Contractor | C6: 2
B7: Delivery Personnel | C7: 2
B8: Domestic Help | C8: 2
B9: Drivers and Conductors | C9: 2
B10: Home Service Providers(Carpenter/Electricians/Plumbers) | C10: 2
B11: Hospitality and Tourism Sector Workers (Non Desk Jobs) | C11: 2
B12: Hotels, Restaurants | C12: 2
B13: Industrial /Manufacturing/Construction | C13: 2
B14: Industrial Workers (Non Hazard workers) | C14: 2
... B21: Security Officers/Guard | C21: 2
B22: Please note: This is illustrative and not an exhaustive list

Sheet Decline List
A2: Decline list
A3: Armed Professionals(Police/CRPF/Army/Navy/Airforce)
A4: Circus Workers and Stunt Artist
A5: Engaged in racing on wheels or horseback
A6: Healthcare workers
A7: Hunters
A8: Industrial Workers(Hazard workers)
A9: Journalist
A10: Political Association
A11: Mountaineer
A12: Politicians
A13: Professional Atheletes
... A28: Please note: This is illustrative and not an exhaustive list
